hyperlpr2/__init__.py
hyperlpr2/hyperlpr.py
hyperlpr2/table_chs.py
hyperlpr2/models/cascade/char/char_single.xml
hyperlpr2/models/cascade/detector/detector_ch.xml
hyperlpr2/models/dnn/HorizonalFinemapping.caffemodel
hyperlpr2/models/dnn/HorizonalFinemapping.prototxt
hyperlpr2/models/dnn/SegmenationFree-Inception.caffemodel
hyperlpr2/models/dnn/SegmenationFree-Inception.prototxt
hyperlpr2/models/dnn/mininet_ssd_v1.caffemodel
hyperlpr2/models/dnn/mininet_ssd_v1.prototxt
hyperlpr2/models/dnn/refinenet.caffemodel
hyperlpr2/models/dnn/refinenet.prototxt
hyperlpr2-2.0.0.dist-info/LICENSE.txt
hyperlpr2-2.0.0.dist-info/METADATA
hyperlpr2-2.0.0.dist-info/WHEEL
hyperlpr2-2.0.0.dist-info/top_level.txt
hyperlpr2-2.0.0.dist-info/RECORD
