Metadata-Version: 2.1
Name: hyperlpr2
Version: 2.0.0
Summary: hyperlpr添加opencv>=4.11与numpy>1.22.0支持
Home-page: https://gitee.com/zeusees/HyperLPR
Author: liu
Author-email: 1003662721@qq.com
Classifier: Programming Language :: Python :: 3
Classifier: License :: OSI Approved :: MIT License
Classifier: Operating System :: OS Independent
Requires-Python: >=3.6
License-File: LICENSE.txt
Requires-Dist: opencv-python
